odoo8_addon_l10n_br_data_base-8.0.1.0.1.99.dev5-py2.7-nspkg.pth
odoo8_addon_l10n_br_data_base-8.0.1.0.1.99.dev5.dist-info/METADATA
odoo8_addon_l10n_br_data_base-8.0.1.0.1.99.dev5.dist-info/RECORD
odoo8_addon_l10n_br_data_base-8.0.1.0.1.99.dev5.dist-info/WHEEL
odoo8_addon_l10n_br_data_base-8.0.1.0.1.99.dev5.dist-info/namespace_packages.txt
odoo8_addon_l10n_br_data_base-8.0.1.0.1.99.dev5.dist-info/top_level.txt
odoo_addons/l10n_br_data_base/README.rst
odoo_addons/l10n_br_data_base/__init__.py
odoo_addons/l10n_br_data_base/__openerp__.py
odoo_addons/l10n_br_data_base/data/res.bank.csv
odoo_addons/l10n_br_data_base/i18n/pt_BR.po
odoo_addons/l10n_br_data_base/static/description/icon.png
